mctool/__init__.py
mctool/buffer.py
mctool/config.py
mctool/dataset.py
mctool-0.0.1a12.dist-info/DESCRIPTION.rst
mctool-0.0.1a12.dist-info/METADATA
mctool-0.0.1a12.dist-info/RECORD
mctool-0.0.1a12.dist-info/WHEEL
mctool-0.0.1a12.dist-info/metadata.json
mctool-0.0.1a12.dist-info/top_level.txt
