Metadata-Version: 2.0
Name: mctool
Version: 0.0.1a12
Summary: machine learning core tool
Home-page: https://gitlab.com/hebinhao1993/mctool
Author: hebinhao
Author-email: hebinhao1993@outlook.com
License: UNKNOWN
Platform: UNKNOWN
Classifier: Programming Language :: Python :: 3
Classifier: License :: OSI Approved :: GNU General Public License v3 (GPLv3)
Classifier: Operating System :: OS Independent
Requires-Dist: h5py
Requires-Dist: numpy
Requires-Dist: pandas
